drip/__init__.py
drip/__version__.py
drip/api/__init__.py
drip/api/accounts.py
drip/api/batches.py
drip/api/broadcasts.py
drip/api/campaigns.py
drip/api/conversions.py
drip/api/custom_fields.py
drip/api/events.py
drip/api/forms.py
drip/api/shoppers.py
drip/api/subscribers.py
drip/api/tags.py
drip/api/users.py
drip/api/webhooks.py
drip/api/workflows.py
drip/client.py
drip/typeshed.py
drip/utils.py
drip_python-0.3.1.dist-info/LICENSE
drip_python-0.3.1.dist-info/WHEEL
drip_python-0.3.1.dist-info/METADATA
drip_python-0.3.1.dist-info/RECORD
