Metadata-Version: 2.1
Name: drip-python
Version: 0.3.1
Summary: Python wrapper for Drip's REST API
Home-page: https://developer.drip.com/
License: MIT
Keywords: drip,api,ecrm,ecommerce,automation
Author: Ross Hodapp
Author-email: ross.hodapp@drip.com
Requires-Python: >=3.7,<4.0
Classifier: Development Status :: 4 - Beta
Classifier: Intended Audience :: Developers
Classifier: License :: OSI Approved :: GNU General Public License v3 or later (GPLv3+)
Classifier: License :: OSI Approved :: MIT License
Classifier: Natural Language :: English
Classifier: Operating System :: OS Independent
Classifier: Programming Language :: Python :: 3
Classifier: Programming Language :: Python :: 3.7
Classifier: Topic :: Communications :: Email
Classifier: Topic :: Internet :: WWW/HTTP :: Dynamic Content
Classifier: Topic :: Utilities
Classifier: Typing :: Typed
Requires-Dist: requests (>=2.22,<3.0)
Requires-Dist: requests-toolbelt (>=0.9.1,<0.10.0)
Project-URL: Repository, https://github.com/DripEmail/drip-python
